zona/__init__.py
zona/_alias_group.py
zona/builder.py
zona/cli.py
zona/config.py
zona/html.py
zona/issues.py
zona/layout.py
zona/lazy_regex.py
zona/links.py
zona/log.py
zona/markdown.py
zona/metadata.py
zona/models.py
zona/parser.py
zona/server.py
zona/templates.py
zona/util.py
zona/websockets.py
zona/data/content/static/style.css
zona/data/server/inject.js
zona/data/templates/base.html
zona/data/templates/basic.html
zona/data/templates/footer.md
zona/data/templates/header.html
zona/data/templates/page.html
zona/data/templates/post_list.html
zona/data/templates/post_nav.html
zona/data/templates/title.html
zona-1.8.0.dist-info/METADATA
zona-1.8.0.dist-info/WHEEL
zona-1.8.0.dist-info/entry_points.txt
zona-1.8.0.dist-info/licenses/LICENSE
zona-1.8.0.dist-info/RECORD
