Metadata-Version: 2.4
Name: zona
Version: 1.8.0
Summary: Opinionated static site generator.
Project-URL: Repository, https://git.ficd.sh/ficd/zona
Author-email: Daniel Fichtinger <daniel@ficd.sh>
License-Expression: BSD-3-Clause
License-File: LICENSE
Requires-Python: >=3.12
Requires-Dist: dacite>=1.9.2
Requires-Dist: feedgen>=1.0.0
Requires-Dist: jinja2>=3.1.6
Requires-Dist: l2m4m>=1.0.4
Requires-Dist: lxml-stubs>=0.5.1
Requires-Dist: lxml>=6.0.2
Requires-Dist: markdown>=3.8.2
Requires-Dist: pygments-ashen>=0.1.3
Requires-Dist: pygments-kakoune>=0.1.0
Requires-Dist: pygments>=2.19.1
Requires-Dist: pymdown-extensions>=10.16
Requires-Dist: python-dateutil>=2.9.0.post0
Requires-Dist: python-frontmatter>=1.1.0
Requires-Dist: readtime>=3.0.0
Requires-Dist: rich>=14.0.0
Requires-Dist: typer>=0.16.0
Requires-Dist: types-lxml>=2025.3.30
Requires-Dist: watchdog>=6.0.0
Requires-Dist: websockets>=15.0.1
